maialib-1.10.0.dist-info/RECORD
maialib-1.10.0.dist-info/WHEEL
maialib-1.10.0.dist-info/top_level.txt
maialib-1.10.0.dist-info/METADATA
maialib-1.10.0.dist-info/licenses/LICENSE.txt
maialib/__init__.py
maialib/setup.py
maialib/xml-scores-examples/Mahler_Symphony_8_Finale.mxl
maialib/xml-scores-examples/Mozart_Requiem_Introitus.mxl
maialib/xml-scores-examples/Dvorak_Symphony_9_mov_4.mxl
maialib/xml-scores-examples/Beethoven_Symphony_5_mov_1.xml
maialib/xml-scores-examples/Chopin_Fantasie_Impromptu.mxl
maialib/xml-scores-examples/Strauss_Also_Sprach_Zarathustra.mxl
maialib/xml-scores-examples/Bach_Cello_Suite_1.mxl
maialib/maiacore/__init__.pyi
maialib/maiacore/__init__.py
maialib/maiacore/maiacore.pyi
maialib/maiacore/maiacore.cpython-310-darwin.so
maialib/maiapy/other.pyi
maialib/maiapy/__init__.pyi
maialib/maiapy/__init__.py
maialib/maiapy/other.py
maialib/maiapy/sethares_dissonance.py
maialib/maiapy/plots.pyi
maialib/maiapy/plots.py
maialib/maiapy/sethares_dissonance.pyi
