Metadata-Version: 2.4
Name: maialib
Version: 1.10.0
Summary: A C++/Python library to manipulate sheet music data
Home-page: https://github.com/nyckmaia/maialib
Author: Nycholas Maia
Author-email: nyckmaia@gmail.com
License: GNU General Public License v3 or later (GPLv3+)
Project-URL: Bug Tracker, https://github.com/nyckmaia/maialib/issues
Keywords: music,score,sheet music,analysis
Classifier: Development Status :: 3 - Alpha
Classifier: Programming Language :: Python :: 3
Classifier: Programming Language :: C++
Classifier: License :: OSI Approved :: GNU General Public License v3 or later (GPLv3+)
Classifier: Operating System :: OS Independent
Classifier: Intended Audience :: Science/Research
Classifier: Natural Language :: English
Classifier: Topic :: Software Development :: Libraries
Requires-Python: >=3.8.0
License-File: LICENSE.txt
Requires-Dist: pandas>=2.0.0
Requires-Dist: plotly
Requires-Dist: kaleido
Requires-Dist: nbformat
Dynamic: author
Dynamic: author-email
Dynamic: classifier
Dynamic: description
Dynamic: description-content-type
Dynamic: home-page
Dynamic: keywords
Dynamic: license
Dynamic: license-file
Dynamic: project-url
Dynamic: requires-dist
Dynamic: requires-python
Dynamic: summary
